exo_horoscope/__init__.py
exo_horoscope/main.py
exo_horoscope/test.py
exo_horoscope/update_exoplanet_catalog.py
exo_horoscope-0.1.3.dist-info/LICENSE
exo_horoscope-0.1.3.dist-info/METADATA
exo_horoscope-0.1.3.dist-info/WHEEL
exo_horoscope-0.1.3.dist-info/top_level.txt
exo_horoscope-0.1.3.dist-info/RECORD
