Metadata-Version: 2.1
Name: exo_horoscope
Version: 0.1.3
License-File: LICENSE
Requires-Dist: numpy >=1.24.0
Requires-Dist: datetime
Requires-Dist: geopy >=2.4.1
Requires-Dist: astropy >=5.3
Requires-Dist: astroquery >=0.4.7
